yp/__init__.py
yp/base.py
yp/deps.py
yp/tools.py
yp/util.py
yp-0.0.11.dist-info/LICENSE
yp-0.0.11.dist-info/METADATA
yp-0.0.11.dist-info/WHEEL
yp-0.0.11.dist-info/top_level.txt
yp-0.0.11.dist-info/RECORD
