Metadata-Version: 2.1
Name: yp
Version: 0.0.11
Summary: A mapping view to pypi projects
Home-page: https://github.com/thorwhalen/yp
Author: Thor Whalen
License: apache-2.0
Platform: any
License-File: LICENSE
Requires-Dist: bs4
Requires-Dist: requests
Requires-Dist: dol
Requires-Dist: lxml
Requires-Dist: pipdeptree
Requires-Dist: packaging
